alfred3_interact/__init__.py
alfred3_interact/_util.py
alfred3_interact/_version.py
alfred3_interact/chat.py
alfred3_interact/element.py
alfred3_interact/group.py
alfred3_interact/match.py
alfred3_interact/member.py
alfred3_interact/page.py
alfred3_interact/quota.py
alfred3_interact/spec.py
alfred3_interact/testutil.py
alfred3_interact/templates/html/ChatElement.html.j2
alfred3_interact/templates/html/ToggleMatchMakerActivation.html.j2
alfred3_interact/templates/html/ViewMembersElement.html.j2
alfred3_interact/templates/js/chat_element.js.j2
alfred3_interact/templates/js/toggle_match_maker.js.j2
alfred3_interact/templates/js/view_members.js.j2
alfred3_interact-0.4.1.dist-info/METADATA
alfred3_interact-0.4.1.dist-info/WHEEL
alfred3_interact-0.4.1.dist-info/licenses/LICENSE
alfred3_interact-0.4.1.dist-info/RECORD
