Metadata-Version: 2.4
Name: alfred3_interact
Version: 0.4.1
Summary: Components for interactive experiments in the alfred3 framework.
Project-URL: Homepage, https://github.com/jobrachem/alfred3-interact
Author: Christian Treffenstädt
Author-email: Johannes Brachem <brachem@uni-goettingen.de>
License: MIT License
License-File: LICENSE
Classifier: License :: OSI Approved :: MIT License
Classifier: Operating System :: OS Independent
Classifier: Programming Language :: Python :: 3
Classifier: Programming Language :: Python :: 3.13
Requires-Python: >=3.13
Requires-Dist: alfred3>=3.0.2
Requires-Dist: bleach>=3.2.1
Requires-Dist: packaging
